etc/__init__.py
openbaton/__init__.py
openbaton/exceptions.py
openbaton/utils.py
openbaton/vnfm.py
python_vnfm_sdk-6.0.0.dist-info/METADATA
python_vnfm_sdk-6.0.0.dist-info/RECORD
python_vnfm_sdk-6.0.0.dist-info/WHEEL
python_vnfm_sdk-6.0.0.dist-info/top_level.txt
tests/__init__.py
tests/simple_test.py
