Metadata-Version: 2.1
Name: python-vnfm-sdk
Version: 6.0.0
Summary: The Python version of the Open Baton vnfm-sdk
Home-page: http://openbaton.github.io/
Author: Open Baton
Author-email: dev@openbaton.org
License: Apache 2
Keywords: python vnfm nfvo open baton openbaton sdk
Platform: UNKNOWN
Classifier: Development Status :: 4 - Beta
Classifier: Intended Audience :: Developers
Classifier: Topic :: Software Development :: Build Tools
Classifier: Topic :: Utilities
Classifier: License :: OSI Approved :: Apache Software License
Requires-Dist: pika
Requires-Dist: futures
